{
  "tabPane": [
    {
      "title": "SmartDashboard",
      "autoPopulate": false,
      "autoPopulatePrefix": "",
      "widgetPane": {
        "gridSize": 32.0,
        "showGrid": true,
        "hgap": 32.0,
        "vgap": 24.0,
        "titleType": 0,
        "tiles": {
          "14,10": {
            "size": [
              9,
              2
            ],
            "content": {
              "_type": "Text View",
              "_source0": "network_table:///SmartDashboard/Estimated Pos",
              "_title": "Odometry Pose",
              "_glyph": 148,
              "_showGlyph": false
            }
          },
          "3,6": {
            "size": [
              4,
              2
            ],
            "content": {
              "_type": "Text View",
              "_source0": "network_table:///SmartDashboard/Speaker",
              "_title": "SPEAKER Tracking",
              "_glyph": 148,
              "_showGlyph": false
            }
          },
          "3,10": {
            "size": [
              4,
              2
            ],
            "content": {
              "_type": "Text View",
              "_source0": "network_table:///SmartDashboard/Note",
              "_title": "NOTE Tracking",
              "_glyph": 148,
              "_showGlyph": false
            }
          },
          "0,8": {
            "size": [
              3,
              2
            ],
            "content": {
              "_type": "Text View",
              "_source0": "network_table:///SmartDashboard/Mode",
              "_title": "Driving Mode",
              "_glyph": 148,
              "_showGlyph": false
            }
          },
          "0,6": {
            "size": [
              3,
              2
            ],
            "content": {
              "_type": "Text View",
              "_source0": "network_table:///SmartDashboard/BatonState",
              "_title": "Baton State",
              "_glyph": 148,
              "_showGlyph": false
            }
          },
          "9,8": {
            "size": [
              2,
              2
            ],
            "content": {
              "_type": "Text View",
              "_source0": "network_table:///SmartDashboard/Intake Range",
              "_title": "Intake",
              "_glyph": 148,
              "_showGlyph": false
            }
          },
          "0,10": {
            "size": [
              3,
              2
            ],
            "content": {
              "_type": "Text View",
              "_source0": "network_table:///SmartDashboard/LED Mode",
              "_title": "LED Mode",
              "_glyph": 148,
              "_showGlyph": false
            }
          },
          "7,6": {
            "size": [
              2,
              2
            ],
            "content": {
              "_type": "Text View",
              "_source0": "network_table:///SmartDashboard/shooter setpoint",
              "_title": "RPM",
              "_glyph": 148,
              "_showGlyph": false
            }
          },
          "0,0": {
            "size": [
              3,
              2
            ],
            "content": {
              "_type": "ComboBox Chooser",
              "_source0": "network_table:///SmartDashboard/Auto Chooser",
              "_title": "Auto Chooser",
              "_glyph": 148,
              "_showGlyph": false
            }
          },
          "9,0": {
            "size": [
              3,
              3
            ],
            "content": {
              "_type": "Boolean Box",
              "_source0": "network_table:///SmartDashboard/ValidNote",
              "_title": "See Note",
              "_glyph": 148,
              "_showGlyph": false,
              "Colors/Color when true": "#00FF00FF",
              "Colors/Color when false": "#CCCCCCFF"
            }
          },
          "12,0": {
            "size": [
              3,
              3
            ],
            "content": {
              "_type": "Boolean Box",
              "_source0": "network_table:///SmartDashboard/ValidSpeaker",
              "_title": "See Speaker",
              "_glyph": 148,
              "_showGlyph": false,
              "Colors/Color when true": "#7CFC00FF",
              "Colors/Color when false": "#CCCCCCFF"
            }
          },
          "6,3": {
            "size": [
              3,
              3
            ],
            "content": {
              "_type": "Boolean Box",
              "_source0": "network_table:///SmartDashboard/bot UTS",
              "_title": "Bottom Shooter",
              "_glyph": 148,
              "_showGlyph": false,
              "Colors/Color when true": "#7CFC00FF",
              "Colors/Color when false": "#8B0000FF"
            }
          },
          "12,3": {
            "size": [
              3,
              3
            ],
            "content": {
              "_type": "Boolean Box",
              "_source0": "network_table:///SmartDashboard/top UTS",
              "_title": "Top Shooter",
              "_glyph": 148,
              "_showGlyph": false,
              "Colors/Color when true": "#7CFC00FF",
              "Colors/Color when false": "#8B0000FF"
            }
          },
          "9,3": {
            "size": [
              3,
              3
            ],
            "content": {
              "_type": "Boolean Box",
              "_source0": "network_table:///SmartDashboard/Ready To Shoot",
              "_title": "Ready To Shoot",
              "_glyph": 148,
              "_showGlyph": false,
              "Colors/Color when true": "#7CFC00FF",
              "Colors/Color when false": "#CCCCCCFF"
            }
          },
          "11,6": {
            "size": [
              3,
              2
            ],
            "content": {
              "_type": "Text View",
              "_source0": "network_table:///SmartDashboard/Robot Heading",
              "_title": "Heading",
              "_glyph": 148,
              "_showGlyph": false
            }
          },
          "7,10": {
            "size": [
              4,
              2
            ],
            "content": {
              "_type": "Text View",
              "_source0": "network_table:///SmartDashboard/Odo Target",
              "_title": "Odo Target",
              "_glyph": 148,
              "_showGlyph": false
            }
          },
          "11,8": {
            "size": [
              3,
              2
            ],
            "content": {
              "_type": "Text View",
              "_source0": "network_table:///SmartDashboard/tilt angle",
              "_title": "Tilt Angle",
              "_glyph": 148,
              "_showGlyph": false
            }
          },
          "7,8": {
            "size": [
              2,
              2
            ],
            "content": {
              "_type": "Text View",
              "_source0": "network_table:///SmartDashboard/tilt setpoint",
              "_title": "Tilt Setpoint",
              "_glyph": 148,
              "_showGlyph": false
            }
          },
          "3,2": {
            "size": [
              3,
              2
            ],
            "content": {
              "_type": "Boolean Box",
              "_source0": "network_table:///SmartDashboard/Note In Intake",
              "_title": "Note In Intake",
              "_glyph": 148,
              "_showGlyph": false,
              "Colors/Color when true": "#00FF00FF",
              "Colors/Color when false": "#FF0000FF"
            }
          },
          "6,0": {
            "size": [
              3,
              3
            ],
            "content": {
              "_type": "Boolean Box",
              "_source0": "network_table:///SmartDashboard/tilt In Position",
              "_title": "Tilt In Position",
              "_glyph": 148,
              "_showGlyph": false,
              "Colors/Color when true": "#00FF00FF",
              "Colors/Color when false": "#8B0000FF"
            }
          },
          "3,8": {
            "size": [
              4,
              2
            ],
            "content": {
              "_type": "Text View",
              "_source0": "network_table:///SmartDashboard/Amp",
              "_title": "Amp Target",
              "_glyph": 148,
              "_showGlyph": false
            }
          },
          "15,0": {
            "size": [
              9,
              9
            ],
            "content": {
              "_type": "Camera Stream",
              "_source0": "camera_server://limelight-note",
              "_title": "limelight-note",
              "_glyph": 148,
              "_showGlyph": false,
              "Crosshair/Show crosshair": true,
              "Crosshair/Crosshair color": "#FFFFFFFF",
              "Controls/Show controls": true,
              "Controls/Rotation": "NONE",
              "compression": -1.0,
              "fps": -1,
              "imageWidth": -1,
              "imageHeight": -1
            }
          },
          "9,6": {
            "size": [
              2,
              2
            ],
            "content": {
              "_type": "Text View",
              "_source0": "network_table:///SmartDashboard/Top RPM",
              "_title": "Top RPM",
              "_glyph": 148,
              "_showGlyph": false
            }
          },
          "0,2": {
            "size": [
              3,
              4
            ],
            "content": {
              "_type": "List Layout",
              "_title": "List Layout",
              "_glyph": 149,
              "_showGlyph": false,
              "Layout/Label position": "BOTTOM",
              "_children": [
                {
                  "_type": "List Layout",
                  "_title": "MANUAL",
                  "_glyph": 149,
                  "_showGlyph": false,
                  "Layout/Label position": "HIDDEN",
                  "_children": [
                    {
                      "_type": "Boolean Box",
                      "_source0": "network_table:///SmartDashboard/Manual Shooting",
                      "_title": "Manual",
                      "_glyph": 148,
                      "_showGlyph": false,
                      "Colors/Color when true": "#7CFC00FF",
                      "Colors/Color when false": "#8B0000FF"
                    },
                    {
                      "_type": "Text View",
                      "_source0": "network_table:///SmartDashboard/Manual Tilt",
                      "_title": "Manual Tilt",
                      "_glyph": 148,
                      "_showGlyph": false
                    },
                    {
                      "_type": "Text View",
                      "_source0": "network_table:///SmartDashboard/Manual Speed",
                      "_title": "Manual Speed",
                      "_glyph": 148,
                      "_showGlyph": false
                    }
                  ]
                }
              ]
            }
          },
          "3,0": {
            "size": [
              3,
              2
            ],
            "content": {
              "_type": "Boolean Box",
              "_source0": "network_table:///SmartDashboard/Note At Shooter",
              "_title": "Note At Shooter",
              "_glyph": 148,
              "_showGlyph": false,
              "Colors/Color when true": "#7CFC00FF",
              "Colors/Color when false": "#8B0000FF"
            }
          },
          "3,4": {
            "size": [
              3,
              2
            ],
            "content": {
              "_type": "Boolean Box",
              "_source0": "network_table:///SmartDashboard/Lift Enable",
              "_title": "Lift Enable",
              "_glyph": 148,
              "_showGlyph": false,
              "Colors/Color when true": "#7CFC00FF",
              "Colors/Color when false": "#8B0000FF"
            }
          }
        }
      }
    },
    {
      "title": "LiveWindow",
      "autoPopulate": true,
      "autoPopulatePrefix": "LiveWindow/",
      "widgetPane": {
        "gridSize": 128.0,
        "showGrid": true,
        "hgap": 16.0,
        "vgap": 16.0,
        "titleType": 0,
        "tiles": {
          "2,3": {
            "size": [
              1,
              1
            ],
            "content": {
              "_type": "Boolean Box",
              "_source0": "network_table:///SmartDashboard/tilt In Position",
              "_title": "/SmartDashboard/tilt In Position",
              "_glyph": 148,
              "_showGlyph": false,
              "Colors/Color when true": "#7CFC00FF",
              "Colors/Color when false": "#8B0000FF"
            }
          }
        }
      }
    },
    {
      "title": "Tab 3",
      "autoPopulate": false,
      "autoPopulatePrefix": "",
      "widgetPane": {
        "gridSize": 128.0,
        "showGrid": true,
        "hgap": 16.0,
        "vgap": 16.0,
        "titleType": 0,
        "tiles": {
          "1,3": {
            "size": [
              1,
              1
            ],
            "content": {
              "_type": "Text View",
              "_source0": "network_table:///SmartDashboard/Manual Speed",
              "_title": "SmartDashboard/Manual Speed",
              "_glyph": 148,
              "_showGlyph": false
            }
          },
          "2,3": {
            "size": [
              1,
              1
            ],
            "content": {
              "_type": "Text View",
              "_source0": "network_table:///SmartDashboard/Manual Tilt",
              "_title": "SmartDashboard/Manual Tilt",
              "_glyph": 148,
              "_showGlyph": false
            }
          },
          "3,3": {
            "size": [
              1,
              1
            ],
            "content": {
              "_type": "Text View",
              "_source0": "network_table:///SmartDashboard/tilt Error",
              "_title": "SmartDashboard/tilt Error",
              "_glyph": 148,
              "_showGlyph": false
            }
          },
          "3,0": {
            "size": [
              1,
              1
            ],
            "content": {
              "_type": "Boolean Box",
              "_source0": "network_table:///SmartDashboard/Lift Enable",
              "_title": "SmartDashboard/Lift Enable",
              "_glyph": 148,
              "_showGlyph": false,
              "Colors/Color when true": "#7CFC00FF",
              "Colors/Color when false": "#8B0000FF"
            }
          },
          "4,0": {
            "size": [
              1,
              1
            ],
            "content": {
              "_type": "Text View",
              "_source0": "network_table:///SmartDashboard/Lift Robot Angle",
              "_title": "/SmartDashboard/Lift Robot Angle",
              "_glyph": 148,
              "_showGlyph": false
            }
          },
          "5,0": {
            "size": [
              1,
              1
            ],
            "content": {
              "_type": "Text View",
              "_source0": "network_table:///SmartDashboard/Lift Turns",
              "_title": "SmartDashboard/Lift Turns",
              "_glyph": 148,
              "_showGlyph": false
            }
          },
          "6,0": {
            "size": [
              1,
              1
            ],
            "content": {
              "_type": "Text View",
              "_source0": "network_table:///SmartDashboard/Lift Power",
              "_title": "SmartDashboard/Lift Power",
              "_glyph": 148,
              "_showGlyph": false
            }
          }
        }
      }
    }
  ],
  "windowGeometry": {
    "x": -7.199999809265137,
    "y": -7.199999809265137,
    "width": 1550.4000244140625,
    "height": 838.4000244140625
  }
}